f0_predictor/__init__.py
f0_predictor/model.py
f0_predictor/predict.py
f0_predictor/smoother.py
f0_predictor/utils.py
f0_predictor-0.1.10.dist-info/METADATA
f0_predictor-0.1.10.dist-info/WHEEL
f0_predictor-0.1.10.dist-info/top_level.txt
f0_predictor-0.1.10.dist-info/RECORD
